dfcsv2parquet/README.MD
dfcsv2parquet/__init__.py
dfcsv2parquet/requirements.txt
dfcsv2parquet/thirdparty.json
dfcsv2parquet-0.10.dist-info/LICENSE.rst
dfcsv2parquet-0.10.dist-info/METADATA
dfcsv2parquet-0.10.dist-info/WHEEL
dfcsv2parquet-0.10.dist-info/top_level.txt
dfcsv2parquet-0.10.dist-info/RECORD
