Metadata-Version: 2.1
Name: dfcsv2parquet
Version: 0.10
Summary: converts large CSV files into smaller, Pandas-compatible Parquet files
Home-page: https://github.com/hansalemaos/dfcsv2parquet
Author: Johannes Fischer
Author-email: aulasparticularesdealemaosp@gmail.com
License: MIT
Keywords: csv,parquet,pandas,DataFrame
Classifier: Development Status :: 4 - Beta
Classifier: Programming Language :: Python :: 3 :: Only
Classifier: Programming Language :: Python :: 3.10
Classifier: Topic :: Software Development :: Libraries :: Python Modules
Classifier: Topic :: Utilities
License-File: LICENSE.rst
Requires-Dist: a-pandas-ex-less-memory-more-speed
Requires-Dist: hackyargparser
Requires-Dist: pandas
Requires-Dist: pyarrow
